pysqlite3/__init__.py
pysqlite3/_sqlite3.cpython-312-x86_64-linux-gnu.so
pysqlite3/dbapi2.py
pysqlite3-binary/_sqlite3.cpython-312-x86_64-linux-gnu.so
pysqlite3_binary.libs/libsqlite3-e9f4411a.so.0.8.6
pysqlite3_binary-0.5.4.post2.dist-info/METADATA
pysqlite3_binary-0.5.4.post2.dist-info/WHEEL
pysqlite3_binary-0.5.4.post2.dist-info/top_level.txt
pysqlite3_binary-0.5.4.post2.dist-info/RECORD
pysqlite3_binary-0.5.4.post2.dist-info/licenses/LICENSE
pysqlite3_binary-0.5.4.post2.dist-info/sboms/auditwheel.cdx.json
